ckanext/__init__.py
ckanext/permissions/__init__.py
ckanext/permissions/cli.py
ckanext/permissions/const.py
ckanext/permissions/helpers.py
ckanext/permissions/model.py
ckanext/permissions/plugin.py
ckanext/permissions/types.py
ckanext/permissions/utils.py
ckanext/permissions/implementation/__init__.py
ckanext/permissions/implementation/permission_labels.py
ckanext/permissions/logic/__init__.py
ckanext/permissions/logic/action.py
ckanext/permissions/logic/auth.py
ckanext/permissions/logic/schema.py
ckanext/permissions/logic/validators.py
ckanext/permissions/migration/permissions/alembic.ini
ckanext/permissions/migration/permissions/env.py
ckanext/permissions/migration/permissions/script.py.mako
ckanext/permissions/migration/permissions/versions/a849104ccfdc_init_tables.py
ckanext/permissions/tests/__init__.py
ckanext/permissions/tests/conftest.py
ckanext/permissions/tests/test_autoassign.py
ckanext/permissions/tests/test_helpers.py
ckanext/permissions/tests/test_permission_labels.py
ckanext/permissions/tests/test_utils.py
ckanext/permissions/tests/test_validators.py
ckanext/permissions/tests/actions/test_permission.py
ckanext/permissions/tests/actions/test_role.py
ckanext/permissions_manager/__init__.py
ckanext/permissions_manager/helpers.py
ckanext/permissions_manager/plugin.py
ckanext/permissions_manager/views.py
ckanext_permissions-0.3.0.dist-info/licenses/LICENSE
ckanext_permissions-0.3.0.dist-info/METADATA
ckanext_permissions-0.3.0.dist-info/WHEEL
ckanext_permissions-0.3.0.dist-info/entry_points.txt
ckanext_permissions-0.3.0.dist-info/top_level.txt
ckanext_permissions-0.3.0.dist-info/RECORD
