Metadata-Version: 2.4
Name: ckanext-permissions
Version: 0.3.0
Summary: Permission system for CKAN
Author-email: DataShades <datashades@linkdigital.com.au>, Oleksandr Cherniavskyi <mutantsan@gmail.com>
Maintainer-email: DataShades <datashades@linkdigital.com.au>
License: AGPL
Project-URL: Homepage, https://github.com/DataShades/ckanext-permissions
Keywords: CKAN
Classifier: Development Status :: 4 - Beta
Classifier: License :: OSI Approved :: GNU Affero General Public License v3 or later (AGPLv3+)
Classifier: Programming Language :: Python :: 3.10
Classifier: Programming Language :: Python :: 3.11
Classifier: Programming Language :: Python :: 3.12
License-File: LICENSE
Provides-Extra: dev
Requires-Dist: pytest-ckan; extra == "dev"
Requires-Dist: pytest-toolbelt; extra == "dev"
Requires-Dist: ckanext-toolbelt; extra == "dev"
Dynamic: license-file
